{
  "project_info": {
    "project_number": "144679913401",
    "project_id": "nexkart-29780",
    "storage_bucket": "nexkart-29780.firebasestorage.app"
  },
  "client": [
    {
      "client_info": {
        "mobilesdk_app_id": "1:144679913401:android:1b8aeeb7c0f39e88789868",
        "android_client_info": {
          "package_name": "com.nexkart"
        }
      },
      "oauth_client": [],
      "api_key": [
        {
          "current_key": "AIzaSyAKiTswxyifHdkQbwUQdmfbsC_ogNhIpvY"
        }
      ],
      "services": {
        "appinvite_service": {
          "other_platform_oauth_client": []
        }
      }
    }
  ],
  "configuration_version": "1"
}